PasswordGenerator/__init__.py
PasswordGenerator/main.py
PasskeyGenerator-0.1.dist-info/LICENCE
PasskeyGenerator-0.1.dist-info/METADATA
PasskeyGenerator-0.1.dist-info/WHEEL
PasskeyGenerator-0.1.dist-info/top_level.txt
PasskeyGenerator-0.1.dist-info/RECORD
