Metadata-Version: 2.1
Name: PasskeyGenerator
Version: 0.1
Summary: This is module generates passwords
Author: chadee
Author-email: esurginet2011@gmail.com
Keywords: password generator
Classifier: Programming Language :: Python :: 3.11
Classifier: License :: OSI Approved :: MIT License
Classifier: Operating System :: OS Independent
Requires-Python: >=3.9
License-File: LICENCE
